karrio/mappers/usps_international/__init__.py
karrio/mappers/usps_international/mapper.py
karrio/mappers/usps_international/proxy.py
karrio/mappers/usps_international/settings.py
karrio/plugins/usps_international/__init__.py
karrio/providers/usps_international/__init__.py
karrio/providers/usps_international/error.py
karrio/providers/usps_international/manifest.py
karrio/providers/usps_international/rate.py
karrio/providers/usps_international/tracking.py
karrio/providers/usps_international/units.py
karrio/providers/usps_international/utils.py
karrio/providers/usps_international/pickup/__init__.py
karrio/providers/usps_international/pickup/cancel.py
karrio/providers/usps_international/pickup/create.py
karrio/providers/usps_international/pickup/update.py
karrio/providers/usps_international/shipment/__init__.py
karrio/providers/usps_international/shipment/cancel.py
karrio/providers/usps_international/shipment/create.py
karrio/schemas/usps_international/__init__.py
karrio/schemas/usps_international/error_response.py
karrio/schemas/usps_international/label_request.py
karrio/schemas/usps_international/label_response.py
karrio/schemas/usps_international/pickup_request.py
karrio/schemas/usps_international/pickup_response.py
karrio/schemas/usps_international/pickup_update_request.py
karrio/schemas/usps_international/pickup_update_response.py
karrio/schemas/usps_international/rate_request.py
karrio/schemas/usps_international/rate_response.py
karrio/schemas/usps_international/scan_form_request.py
karrio/schemas/usps_international/scan_form_response.py
karrio/schemas/usps_international/tracking_response.py
karrio_usps_international-2026.1.4.dist-info/METADATA
karrio_usps_international-2026.1.4.dist-info/WHEEL
karrio_usps_international-2026.1.4.dist-info/entry_points.txt
karrio_usps_international-2026.1.4.dist-info/top_level.txt
karrio_usps_international-2026.1.4.dist-info/RECORD
